deeppoker/server/websocket.py
deeppoker/server/schemas.py
deeppoker/server/app.py
deeppoker/server/__init__.py
deeppoker/server/routes.py
deeppoker/core/card.py
deeppoker/core/hand.py
deeppoker/core/game.py
deeppoker/core/rules.py
deeppoker/core/player.py
deeppoker/core/__init__.py
deeppoker/agents/random_agent.py
deeppoker/agents/__init__.py
deeppoker/agents/base.py
deeppoker/__init__.py
deeppoker-0.1.1.dist-info/WHEEL
deeppoker-0.1.1.dist-info/entry_points.txt
deeppoker-0.1.1.dist-info/METADATA
deeppoker-0.1.1.dist-info/RECORD
