Metadata-Version: 2.3
Name: deeppoker
Version: 0.1.1
Summary: DeepPoker R1 - A Texas Hold'em poker game engine with FastAPI WebSocket server and AI agent framework
Keywords: poker,texasholdem,holdem,game,ai,agent
Author: Ziyi
Author-email: Ziyi <ziyigogogo@gmail.com>
License: MIT
Classifier: Development Status :: 3 - Alpha
Classifier: Intended Audience :: Developers
Classifier: License :: OSI Approved :: MIT License
Classifier: Programming Language :: Python :: 3
Classifier: Programming Language :: Python :: 3.10
Classifier: Programming Language :: Python :: 3.11
Classifier: Programming Language :: Python :: 3.12
Classifier: Topic :: Games/Entertainment
Requires-Dist: fastapi>=0.109.0
Requires-Dist: uvicorn[standard]>=0.27.0
Requires-Dist: websockets>=12.0
Requires-Dist: pydantic>=2.5.0
Requires-Dist: jinja2>=3.1.0
Requires-Dist: python-multipart>=0.0.6
Requires-Dist: pytest>=8.0.0 ; extra == 'dev'
Requires-Dist: pytest-asyncio>=0.23.0 ; extra == 'dev'
Requires-Dist: httpx>=0.26.0 ; extra == 'dev'
Requires-Python: >=3.10
Provides-Extra: dev
